approck_services/__init__.py
approck_services/base.py
approck_services/fastapi.py
approck_services/integrations/__init__.py
approck_services/integrations/upload.py
approck_services/sqlalchemy/__init__.py
approck_services/sqlalchemy/abstract.py
approck_services/sqlalchemy/base.py
approck_services-1.0.7.dist-info/METADATA
approck_services-1.0.7.dist-info/WHEEL
approck_services-1.0.7.dist-info/RECORD
